Workbook

Sheet Stato Patrimoniale
A1: FIDIA FARMACEUTICI S.p.A. — Balance Sheet
A2: Stato Patrimoniale Consolidato — valori in migliaia di Euro, salvo diversa indicazione | V2: Tabella di supporto ai grafici
V3: Anno | W3: Totale Attivo | X3: Patrimonio Netto
A4: 1. STATO PATRIMONIALE CONSOLIDATO IFRS | V4: 2021 | W4: =B131 -> 575976 | X4: =B133 -> 212041
A5: Voce | B5: Nota | C5: 31/12/2025 | D5: 31/12/2024 | E5: Variazione | F5: Var % | V5: 2022 | W5: =C131 -> 640290 | X5: =C133 -> 255622
A6: ATTIVO | V6: 2023 | W6: =D131 -> 655310 | X6: =D133 -> 291845
A7: Attività non correnti | V7: 2024 | W7: =E131 -> 797546 | X7: =E133 -> 329380
A8: Immobili, impianti e macchinari | B8: 4.1 | C8: 133751 | D8: 124113 | E8: =C8-D8 -> 9638 | F8: =IFERROR(E8/ABS(D8),"n.s.") -> 0.07765504 | V8: 2025 | W8: =F131 -> 841669 | X8: =F133 -> 362731
A9: Attività immateriali | B9: 4.2 | C9: 230170 | D9: 229289 | E9: =C9-D9 -> 881 | F9: =IFERROR(E9/ABS(D9),"n.s.") -> 0.0038423125
A10: Avviamenti | B10: 4.3 | C10: 113611 | D10: 110080 | E10: =C10-D10 -> 3531 | F10: =IFERROR(E10/ABS(D10),"n.s.") -> 0.032076672 | V10: Tabella di supporto ai grafici
A11: Partecipazioni | B11: 4.4 | C11: 38671 | D11: 24 | E11: =C11-D11 -> 38647 | F11: =IFERROR(E11/ABS(D11),"n.s.") -> 1610.2917 | V11: Anno | W11: Debiti a breve | X11: Debiti a m/l | Y11: Patrimonio Netto
A12: Altre partecipazioni e titoli | B12: 4.4 | C12: 89 | D12: 89 | E12: =C12-D12 -> 0 | F12: =IFERROR(E12/ABS(D12),"n.s.") -> 0 | V12: 2024 | W12: =D96 -> 247514 | X12: =D105 -> 220650 | Y12: =D108 -> 329380
A13: Crediti | B13: 4.5 | C13: 1064 | D13: 1374 | E13: =C13-D13 -> -310 | F13: =IFERROR(E13/ABS(D13),"n.s.") -> -0.22561863 | V13: 2025 | W13: =C96 -> 187427 | X13: =C105 -> 291510 | Y13: =C108 -> 362731
A14: Attività fiscali differite | B14: 4.6 | C14: 26035 | D14: 20366 | E14: =C14-D14 -> 5669 | F14: =IFERROR(E14/ABS(D14),"n.s.") -> 0.27835608
A15: Totale attività non correnti | C15: =SUM(C8:C14) -> 543391 | D15: =SUM(D8:D14) -> 485335 | E15: =C15-D15 -> 58056 | F15: =IFERROR(E15/ABS(D15),"n.s.") -> 0.11962047
A17: Attività correnti
A18: Rimanenze di magazzino | B18: 4.7 | C18: 88484 | D18: 89686 | E18: =C18-D18 -> -1202 | F18: =IFERROR(E18/ABS(D18),"n.s.") -> -0.013402315
A19: Crediti commerciali | B19: 4.8 | C19: 141729 | D19: 148997 | E19: =C19-D19 -> -7268 | F19: =IFERROR(E19/ABS(D19),"n.s.") -> -0.048779506
A20: Crediti tributari | B20: 4.9 | C20: 15581 | D20: 5624 | E20: =C20-D20 -> 9957 | F20: =IFERROR(E20/ABS(D20),"n.s.") -> 1.7704481
A21: Altre attività correnti | B21: 4.10 | C21: 15281 | D21: 19087 | E21: =C21-D21 -> -3806 | F21: =IFERROR(E21/ABS(D21),"n.s.") -> -0.19940273
A22: Strumenti derivati valutati al fair value | B22: 4.11 | C22: 188 | D22: 1162 | E22: =C22-D22 -> -974 | F22: =IFERROR(E22/ABS(D22),"n.s.") -> -0.83820998
A23: Investimenti finanziari a breve termine e disponibilità liquide | B23: 4.12 | C23: 37015 | D23: 47655 | E23: =C23-D23 -> -10640 | F23: =IFERROR(E23/ABS(D23),"n.s.") -> -0.22327143
A24: Totale attività correnti | C24: =SUM(C18:C23) -> 298278 | D24: =SUM(D18:D23) -> 312211 | E24: =C24-D24 -> -13933 | F24: =IFERROR(E24/ABS(D24),"n.s.") -> -0.044626871
A26: TOTALE ATTIVO | C26: =C15+C24 -> 841669 | D26: =D15+D24 -> 797546 | E26: =C26-D26 -> 44123 | F26: =IFERROR(E26/ABS(D26),"n.s.") -> 0.055323455
A28: PASSIVO E PATRIMONIO NETTO
A29: Patrimonio netto
A30: Capitale sociale | C30: 36120 | D30: 36120 | E30: =C30-D30 -> 0 | F30: =IFERROR(E30/ABS(D30),"n.s.") -> 0
A31: Riserva sovrapprezzo azioni | C31: 0 | D31: 0 | E31: =C31-D31 -> 0 | F31: =IFERROR(E31/ABS(D31),"n.s.") -> n.s.
A32: Azioni proprie | C32: 0 | D32: 0 | E32: =C32-D32 -> 0 | F32: =IFERROR(E32/ABS(D32),"n.s.") -> n.s.
A33: Riserva azioni società controllante | C33: 38648 | D33: 0 | E33: =C33-D33 -> 38648 | F33: =IFERROR(E33/ABS(D33),"n.s.") -> n.s.
A34: Riserva per strumenti finanziari derivati al fair value | C34: -873 | D34: -692 | E34: =C34-D34 -> -181 | F34: =IFERROR(E34/ABS(D34),"n.s.") -> -0.26156069
A35: Differenza da conversione dei bilanci in valuta estera | C35: 317 | D35: 2323 | E35: =C35-D35 -> -2006 | F35: =IFERROR(E35/ABS(D35),"n.s.") -> -0.86353853
A36: Altre riserve | C36: 8194 | D36: 7786 | E36: =C36-D36 -> 408 | F36: =IFERROR(E36/ABS(D36),"n.s.") -> 0.052401747
A37: Riserva First Time Adoption | C37: 8953 | D37: 8953 | E37: =C37-D37 -> 0 | F37: =IFERROR(E37/ABS(D37),"n.s.") -> 0
A38: Utili indivisi | C38: 231717 | D38: 232774 | E38: =C38-D38 -> -1057 | F38: =IFERROR(E38/ABS(D38),"n.s.") -> -0.0045408852
A39: Risultato netto dell'esercizio | C39: ='Conto Economico'!C18 -> 39655 | D39: ='Conto Economico'!D18 -> 42116 | E39: =C39-D39 -> -2461 | F39: =IFERROR(E39/ABS(D39),"n.s.") -> -0.058433849
A40: Acconto sul dividendo | C40: 0 | D40: 0 | E40: =C40-D40 -> 0 | F40: =IFERROR(E40/ABS(D40),"n.s.") -> n.s.
A41: Totale patrimonio netto | B41: 4.13 | C41: =SUM(C30:C40) -> 362731 | D41: =SUM(D30:D40) -> 329380 | E41: =C41-D41 -> 33351 | F41: =IFERROR(E41/ABS(D41),"n.s.") -> 0.10125387
A43: Passività non correnti
A44: Finanziamenti dovuti oltre un anno | B44: 4.14 | C44: 273941 | D44: 203334 | E44: =C44-D44 -> 70607 | F44: =IFERROR(E44/ABS(D44),"n.s.") -> 0.3472464
A45: Trattamento di fine rapporto e altri benefici | B45: 4.15 | C45: 7527 | D45: 8222 | E45: =C45-D45 -> -695 | F45: =IFERROR(E45/ABS(D45),"n.s.") -> -0.084529312
A46: Passività per imposte differite | B46: 4.17 | C46: 4813 | D46: 2957 | E46: =C46-D46 -> 1856 | F46: =IFERROR(E46/ABS(D46),"n.s.") -> 0.62766317
A47: Fondi per rischi e oneri | B47: 4.16 | C47: 3930 | D47: 3767 | E47: =C47-D47 -> 163 | F47: =IFERROR(E47/ABS(D47),"n.s.") -> 0.043270507
A48: Strumenti derivati valutati al fair value | B48: 4.18 | C48: 1299 | D48: 2370 | E48: =C48-D48 -> -1071 | F48: =IFERROR(E48/ABS(D48),"n.s.") -> -0.45189873
A49: Altri debiti | B49: 4.19 | C49: 0 | D49: 0 | E49: =C49-D49 -> 0 | F49: =IFERROR(E49/ABS(D49),"n.s.") -> n.s.
A50: Totale passività non correnti | C50: =SUM(C44:C49) -> 291510 | D50: =SUM(D44:D49) -> 220650 | E50: =C50-D50 -> 70860 | F50: =IFERROR(E50/ABS(D50),"n.s.") -> 0.32114208
A52: Passività correnti
A53: Debiti commerciali | B53: 4.20 | C53: 59197 | D53: 68801 | E53: =C53-D53 -> -9604 | F53: =IFERROR(E53/ABS(D53),"n.s.") -> -0.13959099
A54: Debiti tributari | B54: 4.21 | C54: 3908 | D54: 8177 | E54: =C54-D54 -> -4269 | F54: =IFERROR(E54/ABS(D54),"n.s.") -> -0.52207411
A55: Altre passività correnti | B55: 4.22 | C55: 52335 | D55: 50817 | E55: =C55-D55 -> 1518 | F55: =IFERROR(E55/ABS(D55),"n.s.") -> 0.029871893
A56: Fondi per rischi e oneri | B56: 4.23 | C56: 1100 | D56: 1400 | E56: =C56-D56 -> -300 | F56: =IFERROR(E56/ABS(D56),"n.s.") -> -0.21428571
A57: Strumenti derivati valutati al fair value | B57: 4.24 | C57: 0 | D57: 0 | E57: =C57-D57 -> 0 | F57: =IFERROR(E57/ABS(D57),"n.s.") -> n.s.
A58: Finanziamenti dovuti entro un anno | B58: 4.25 | C58: 70887 | D58: 118319 | E58: =C58-D58 -> -47432 | F58: =IFERROR(E58/ABS(D58),"n.s.") -> -0.40088236
A59: Totale passività correnti | C59: =SUM(C53:C58) -> 187427 | D59: =SUM(D53:D58) -> 247514 | E59: =C59-D59 -> -60087 | F59: =IFERROR(E59/ABS(D59),"n.s.") -> -0.24276203
A61: TOTALE PATRIMONIO NETTO E PASSIVITÀ | C61: =C41+C50+C59 -> 841668 | D61: =D41+D50+D59 -> 797544 | E61: =C61-D61 -> 44124 | F61: =IFERROR(E61/ABS(D61),"n.s.") -> 0.055324847
A62: Verifica di quadratura (Totale attivo − Totale PN e passività) | C62: =C26-C61 -> 1 | D62: =D26-D61 -> 2
A64: Fonte: Fidia Farmaceutici S.p.A., Bilancio Consolidato al 31/12/2025, «Situazione patrimoniale e finanziaria consolidata», pagg. 72-73/89, Note 4.1-4.25 (documento depositato, conforme all'originale ai sensi dell'art. 31 c. 2-quinquies L. 340/2000). Valori in migliaia di Euro. La voce «Risultato netto dell'esercizio» è collegata al Conto Economico (cella C18/D18) per garantire la coerenza tra i tre prospetti («three statement»).
A67: 2. STATO PATRIMONIALE RICLASSIFICATO — METODO ICAS (schema finanziario CERVED, per liquidità ed esigibilità)
A69: Voce | B69: Nota | C69: 31/12/2025 | D69: 31/12/2024 | E69: Variazione | F69: Var %
A70: IMPIEGHI (ATTIVO)
A71: Liquidità immediate (disponibilità liquide e mezzi equivalenti) | C71: =C23 -> 37015 | D71: =D23 -> 47655 | E71: =C71-D71 -> -10640 | F71: =IFERROR(E71/ABS(D71),"n.s.") -> -0.22327143
A72: Liquidità differite:
A73: Crediti commerciali | C73: =C19 -> 141729 | D73: =D19 -> 148997 | E73: =C73-D73 -> -7268 | F73: =IFERROR(E73/ABS(D73),"n.s.") -> -0.048779506
A74: Crediti tributari | C74: =C20 -> 15581 | D74: =D20 -> 5624 | E74: =C74-D74 -> 9957 | F74: =IFERROR(E74/ABS(D74),"n.s.") -> 1.7704481
A75: Altre attività correnti | C75: =C21 -> 15281 | D75: =D21 -> 19087 | E75: =C75-D75 -> -3806 | F75: =IFERROR(E75/ABS(D75),"n.s.") -> -0.19940273
A76: Strumenti derivati al fair value | C76: =C22 -> 188 | D76: =D22 -> 1162 | E76: =C76-D76 -> -974 | F76: =IFERROR(E76/ABS(D76),"n.s.") -> -0.83820998
A77: Totale liquidità differite | C77: =SUM(C73:C76) -> 172779 | D77: =SUM(D73:D76) -> 174870 | E77: =C77-D77 -> -2091 | F77: =IFERROR(E77/ABS(D77),"n.s.") -> -0.011957454
A78: Rimanenze | C78: =C18 -> 88484 | D78: =D18 -> 89686 | E78: =C78-D78 -> -1202 | F78: =IFERROR(E78/ABS(D78),"n.s.") -> -0.013402315
A79: TOTALE ATTIVO CIRCOLANTE (Capitale Circolante Lordo) | C79: =C71+C77+C78 -> 298278 | D79: =D71+D77+D78 -> 312211 | E79: =C79-D79 -> -13933 | F79: =IFERROR(E79/ABS(D79),"n.s.") -> -0.044626871
A81: Immobilizzazioni (Attivo Fisso):
A82: Immobilizzazioni immateriali (incl. avviamento) | C82: =C9+C10 -> 343781 | D82: =D9+D10 -> 339369 | E82: =C82-D82 -> 4412 | F82: =IFERROR(E82/ABS(D82),"n.s.") -> 0.013000598
A83: Immobilizzazioni materiali | C83: =C8 -> 133751 | D83: =D8 -> 124113 | E83: =C83-D83 -> 9638 | F83: =IFERROR(E83/ABS(D83),"n.s.") -> 0.07765504
A84: Immobilizzazioni finanziarie (partecipazioni, crediti e imposte anticipate) | C84: =C11+C12+C13+C14 -> 65859 | D84: =D11+D12+D13+D14 -> 21853 | E84: =C84-D84 -> 44006 | F84: =IFERROR(E84/ABS(D84),"n.s.") -> 2.0137281
A85: TOTALE ATTIVO FISSO (Immobilizzazioni nette) | C85: =C82+C83+C84 -> 543391 | D85: =D82+D83+D84 -> 485335 | E85: =C85-D85 -> 58056 | F85: =IFERROR(E85/ABS(D85),"n.s.") -> 0.11962047
A86: TOTALE IMPIEGHI | C86: =C79+C85 -> 841669 | D86: =D79+D85 -> 797546 | E86: =C86-D86 -> 44123 | F86: =IFERROR(E86/ABS(D86),"n.s.") -> 0.055323455
A88: FONTI (PASSIVO E PATRIMONIO NETTO)
A89: Debiti a breve termine (Passività correnti):
A90: Debiti finanziari a breve termine | C90: =C58 -> 70887 | D90: =D58 -> 118319 | E90: =C90-D90 -> -47432 | F90: =IFERROR(E90/ABS(D90),"n.s.") -> -0.40088236
A91: Debiti commerciali | C91: =C53 -> 59197 | D91: =D53 -> 68801 | E91: =C91-D91 -> -9604 | F91: =IFERROR(E91/ABS(D91),"n.s.") -> -0.13959099
A92: Debiti tributari | C92: =C54 -> 3908 | D92: =D54 -> 8177 | E92: =C92-D92 -> -4269 | F92: =IFERROR(E92/ABS(D92),"n.s.") -> -0.52207411
A93: Altre passività correnti | C93: =C55 -> 52335 | D93: =D55 -> 50817 | E93: =C93-D93 -> 1518 | F93: =IFERROR(E93/ABS(D93),"n.s.") -> 0.029871893
A94: Fondi per rischi e oneri (quota breve) | C94: =C56 -> 1100 | D94: =D56 -> 1400 | E94: =C94-D94 -> -300 | F94: =IFERROR(E94/ABS(D94),"n.s.") -> -0.21428571
A95: Strumenti derivati al fair value (quota corrente) | C95: =C57 -> 0 | D95: =D57 -> 0 | E95: =C95-D95 -> 0 | F95: =IFERROR(E95/ABS(D95),"n.s.") -> n.s.
A96: TOTALE DEBITI A BREVE TERMINE | C96: =SUM(C90:C95) -> 187427 | D96: =SUM(D90:D95) -> 247514 | E96: =C96-D96 -> -60087 | F96: =IFERROR(E96/ABS(D96),"n.s.") -> -0.24276203
A98: Debiti a medio-lungo termine (Passività consolidate):
A99: Debiti finanziari a medio-lungo termine | C99: =C44 -> 273941 | D99: =D44 -> 203334 | E99: =C99-D99 -> 70607 | F99: =IFERROR(E99/ABS(D99),"n.s.") -> 0.3472464
A100: Trattamento di fine rapporto e altri benefici | C100: =C45 -> 7527 | D100: =D45 -> 8222 | E100: =C100-D100 -> -695 | F100: =IFERROR(E100/ABS(D100),"n.s.") -> -0.084529312
A101: Fondi per rischi e oneri (quota lungo) | C101: =C47 -> 3930 | D101: =D47 -> 3767 | E101: =C101-D101 -> 163 | F101: =IFERROR(E101/ABS(D101),"n.s.") -> 0.043270507
A102: Passività per imposte differite | C102: =C46 -> 4813 | D102: =D46 -> 2957 | E102: =C102-D102 -> 1856 | F102: =IFERROR(E102/ABS(D102),"n.s.") -> 0.62766317
A103: Strumenti derivati al fair value (quota non corrente) | C103: =C48 -> 1299 | D103: =D48 -> 2370 | E103: =C103-D103 -> -1071 | F103: =IFERROR(E103/ABS(D103),"n.s.") -> -0.45189873
A104: Altri debiti | C104: =C49 -> 0 | D104: =D49 -> 0 | E104: =C104-D104 -> 0 | F104: =IFERROR(E104/ABS(D104),"n.s.") -> n.s.
A105: TOTALE DEBITI A MEDIO-LUNGO TERMINE | C105: =SUM(C99:C104) -> 291510 | D105: =SUM(D99:D104) -> 220650 | E105: =C105-D105 -> 70860 | F105: =IFERROR(E105/ABS(D105),"n.s.") -> 0.32114208
A106: TOTALE DEBITI (Capitale di terzi) | C106: =C96+C105 -> 478937 | D106: =D96+D105 -> 468164 | E106: =C106-D106 -> 10773 | F106: =IFERROR(E106/ABS(D106),"n.s.") -> 0.023011167
A108: Patrimonio netto | C108: =C41 -> 362731 | D108: =D41 -> 329380 | E108: =C108-D108 -> 33351 | F108: =IFERROR(E108/ABS(D108),"n.s.") -> 0.10125387
A109: TOTALE FONTI | C109: =C106+C108 -> 841668 | D109: =D106+D108 -> 797544 | E109: =C109-D109 -> 44124 | F109: =IFERROR(E109/ABS(D109),"n.s.") -> 0.055324847
A110: Verifica di quadratura (Impieghi − Fonti) | C110: =C86-C109 -> 1 | D110: =D86-D109 -> 2
A112: 3. INDICATORI STRUTTURALI
A113: Indicatore | C113: 31/12/2025 | D113: 31/12/2024 | E113: Variazione
A114: Capitale Circolante Netto (CCN = Attivo circ. − Debiti a breve) | C114: =C79-C96 -> 110851 | D114: =D79-D96 -> 64697 | E114: =C114-D114 -> 46154 | F114: =IFERROR(E114/ABS(D114),"n.s.") -> 0.71338702
A115: Capitale Circolante Netto Commerciale (Crediti comm. + Rimanenze − Debiti comm.) | C115: =C19+C18-C53 -> 171016 | D115: =D19+D18-D53 -> 169882 | E115: =C115-D115 -> 1134 | F115: =IFERROR(E115/ABS(D115),"n.s.") -> 0.0066752216
...

Sheet Conto Economico
A1: FIDIA FARMACEUTICI S.p.A. — Income Statement
A2: Conto Economico Consolidato — valori in migliaia di Euro, salvo diversa indicazione | V2: Tabella di supporto ai grafici
V3: Anno | W3: Fatturato | X3: EBITDA | Y3: EBIT | Z3: Utile Netto
A4: 1. CONTO ECONOMICO CONSOLIDATO IFRS (schema per destinazione di costo, ai sensi IAS 1) | V4: 2021 | W4: =B54 -> 358539 | X4: =B65 -> 65971.176 | Y4: =B66 -> 53780.85 | Z4: =B67 -> 36471
A5: Voce | B5: Nota | C5: 31/12/2025 | D5: 31/12/2024 | E5: Variazione | F5: Var % | V5: 2022 | W5: =C54 -> 412074 | X5: =C65 -> 80354.43 | Y5: =C66 -> 51509.25 | Z5: =C67 -> 37832
A6: Ricavi netti | B6: 5.1 | C6: 538343 | D6: 510120 | E6: =C6-D6 -> 28223 | F6: =IFERROR(E6/ABS(D6),"n.s.") -> 0.055326198 | V6: 2023 | W6: =D54 -> 454199 | X6: =D65 -> 89477.203 | Y6: =D66 -> 62679.462 | Z6: =D67 -> 45236
A7: Costo del venduto | B7: 5.2 | C7: -215762 | D7: -200087 | E7: =C7-D7 -> -15675 | F7: =IFERROR(E7/ABS(D7),"n.s.") -> -0.078340922 | V7: 2024 | W7: =E54 -> 510120 | X7: =E65 -> 97513 | Y7: =E66 -> 68986 | Z7: =E67 -> 42116
A8: Risultato operativo lordo (Gross Profit) | C8: =C6+C7 -> 322581 | D8: =D6+D7 -> 310033 | E8: =C8-D8 -> 12548 | F8: =IFERROR(E8/ABS(D8),"n.s.") -> 0.040473111 | V8: 2025 | W8: =F54 -> 538343 | X8: =F65 -> 110124 | Y8: =F66 -> 60138 | Z8: =F67 -> 39655
A9: Spese di vendita | B9: 5.2 | C9: -153011 | D9: -150063 | E9: =C9-D9 -> -2948 | F9: =IFERROR(E9/ABS(D9),"n.s.") -> -0.019645082
A10: Spese di ricerca e sviluppo | B10: 5.2 | C10: -41733 | D10: -29285 | E10: =C10-D10 -> -12448 | F10: =IFERROR(E10/ABS(D10),"n.s.") -> -0.42506403
A11: Spese generali e amministrative | B11: 5.2 | C11: -69055 | D11: -63039 | E11: =C11-D11 -> -6016 | F11: =IFERROR(E11/ABS(D11),"n.s.") -> -0.095432986 | V11: Tabella di supporto ai grafici
A12: Altri (oneri)/proventi netti | B12: 5.2 | C12: 1356 | D12: 1340 | E12: =C12-D12 -> 16 | F12: =IFERROR(E12/ABS(D12),"n.s.") -> 0.011940299 | V12: Anno | W12: ROS | X12: MOL/Ricavi | Y12: ROA | Z12: ROE
A13: Totale costi operativi | C13: =SUM(C9:C12) -> -262443 | D13: =SUM(D9:D12) -> -241047 | E13: =C13-D13 -> -21396 | F13: =IFERROR(E13/ABS(D13),"n.s.") -> -0.088762772 | V13: 2021 | W13: =B58 -> 0.15 | X13: =B59 -> 0.184 | Y13: =B60 -> 0.094 | Z13: =B61 -> 0.172
A14: RISULTATO OPERATIVO (EBIT) | C14: =C8+C13 -> 60138 | D14: =D8+D13 -> 68986 | E14: =C14-D14 -> -8848 | F14: =IFERROR(E14/ABS(D14),"n.s.") -> -0.12825791 | V14: 2022 | W14: =C58 -> 0.125 | X14: =C59 -> 0.195 | Y14: =C60 -> 0.081 | Z14: =C61 -> 0.148
A15: (Oneri)/proventi finanziari netti | B15: 5.3 | C15: -13728 | D15: -5299 | E15: =C15-D15 -> -8429 | F15: =IFERROR(E15/ABS(D15),"n.s.") -> -1.5906775 | V15: 2023 | W15: =D58 -> 0.138 | X15: =D59 -> 0.197 | Y15: =D60 -> 0.096 | Z15: =D61 -> 0.155
A16: Risultato prima delle imposte | C16: =C14+C15 -> 46410 | D16: =D14+D15 -> 63687 | E16: =C16-D16 -> -17277 | F16: =IFERROR(E16/ABS(D16),"n.s.") -> -0.27127985 | V16: 2024 | W16: =E58 -> 0.13523485 | X16: =E59 -> 0.19115698 | Y16: =E60 -> 0.086497832 | Z16: =E61 -> 0.12786447
A17: Imposte | B17: 5.4 | C17: -6755 | D17: -21571 | E17: =C17-D17 -> 14816 | F17: =IFERROR(E17/ABS(D17),"n.s.") -> 0.68684808 | V17: 2025 | W17: =F58 -> 0.11170945 | X17: =F59 -> 0.20456103 | Y17: =F60 -> 0.071450891 | Z17: =F61 -> 0.10932344
A18: UTILE NETTO DELL'ESERCIZIO | C18: =C16+C17 -> 39655 | D18: =D16+D17 -> 42116 | E18: =C18-D18 -> -2461 | F18: =IFERROR(E18/ABS(D18),"n.s.") -> -0.058433849
A20: Dati complementari (fonte: Relazione sulla Gestione — Principali dati economici consolidati)
A21: di cui: Ammortamenti e svalutazioni | C21: -49986 | D21: -28527 | E21: =C21-D21 -> -21459 | F21: =IFERROR(E21/ABS(D21),"n.s.") -> -0.75223472
A22: EBITDA (Margine Operativo Lordo) | C22: =C14-C21 -> 110124 | D22: =D14-D21 -> 97513 | E22: =C22-D22 -> 12611 | F22: =IFERROR(E22/ABS(D22),"n.s.") -> 0.12932635
A23: EBITDA margin (EBITDA / Ricavi netti) | C23: =C22/C6 -> 0.20456103 | D23: =D22/D6 -> 0.19115698
A25: Fonte: Fidia Farmaceutici S.p.A., Bilancio Consolidato al 31/12/2025, «Conto Economico Consolidato», pag. 74/89 (Note 5.1-5.4), e Relazione sulla Gestione — «Principali dati economici consolidati», pag. 51/89 (per Ammortamenti/EBITDA). Valori in migliaia di Euro. Il totale «Risultato operativo» ricalcolato per formula (C14) può differire di ±1 migliaia di Euro dal dato pubblicato per arrotondamento.
A28: 2. CONTO ECONOMICO RICLASSIFICATO — METODO ICAS (a valore aggiunto / EBITDA)
A29: Voce | B29: Nota | C29: 31/12/2025 | D29: 31/12/2024 | E29: Variazione | F29: Var %
A30: Valore della produzione (Ricavi netti) | C30: =C6 -> 538343 | D30: =D6 -> 510120 | E30: =C30-D30 -> 28223 | F30: =IFERROR(E30/ABS(D30),"n.s.") -> 0.055326198
A31: Costi della produzione (mat. prime, servizi, personale — stima da ponte EBITDA) | C31: =-(C30-C22) -> -428219 | D31: =-(D30-D22) -> -412607 | E31: =C31-D31 -> -15612 | F31: =IFERROR(E31/ABS(D31),"n.s.") -> -0.037837458
A32: MOL / EBITDA (Margine Operativo Lordo) | C32: =C30+C31 -> 110124 | D32: =D30+D31 -> 97513 | E32: =C32-D32 -> 12611 | F32: =IFERROR(E32/ABS(D32),"n.s.") -> 0.12932635
A33: Ammortamenti, svalutazioni e accantonamenti | C33: =C21 -> -49986 | D33: =D21 -> -28527 | E33: =C33-D33 -> -21459 | F33: =IFERROR(E33/ABS(D33),"n.s.") -> -0.75223472
A34: EBIT (Risultato Operativo) | C34: =C32+C33 -> 60138 | D34: =D32+D33 -> 68986 | E34: =C34-D34 -> -8848 | F34: =IFERROR(E34/ABS(D34),"n.s.") -> -0.12825791
A35: Proventi/(oneri) della gestione finanziaria | C35: =C15 -> -13728 | D35: =D15 -> -5299 | E35: =C35-D35 -> -8429 | F35: =IFERROR(E35/ABS(D35),"n.s.") -> -1.5906775
A36: Risultato ante imposte (EBT) | C36: =C34+C35 -> 46410 | D36: =D34+D35 -> 63687 | E36: =C36-D36 -> -17277 | F36: =IFERROR(E36/ABS(D36),"n.s.") -> -0.27127985
A37: Imposte sul reddito | C37: =C17 -> -6755 | D37: =D17 -> -21571 | E37: =C37-D37 -> 14816 | F37: =IFERROR(E37/ABS(D37),"n.s.") -> 0.68684808
A38: RISULTATO NETTO | C38: =C36+C37 -> 39655 | D38: =D36+D37 -> 42116 | E38: =C38-D38 -> -2461 | F38: =IFERROR(E38/ABS(D38),"n.s.") -> -0.058433849
A40: 3. INDICATORI DI REDDITIVITÀ ICAS
A41: Indicatore | C41: 31/12/2025 | D41: 31/12/2024 | E41: Variazione
A42: MOL margin (MOL / Ricavi netti) | C42: =C32/C30 -> 0.20456103 | D42: =D32/D30 -> 0.19115698 | E42: =C42-D42 -> 0.01340405 | F42: =IFERROR(E42/ABS(D42),"n.s.") -> 0.07012064
A43: EBITDA margin | C43: =C22/C6 -> 0.20456103 | D43: =D22/D6 -> 0.19115698 | E43: =C43-D43 -> 0.01340405 | F43: =IFERROR(E43/ABS(D43),"n.s.") -> 0.07012064
A44: ROS — Return on Sales (EBIT / Ricavi netti) | C44: =C34/C30 -> 0.11170945 | D44: =D34/D30 -> 0.13523485 | E44: =C44-D44 -> -0.023525398 | F44: =IFERROR(E44/ABS(D44),"n.s.") -> -0.17395958
A45: Asset Turnover (Ricavi netti / Totale Attivo) | C45: =C30/'Stato Patrimoniale'!C26 -> 0.63961367 | D45: =D30/'Stato Patrimoniale'!D26 -> 0.63961201 | E45: =C45-D45 -> 1.662518e-06 | F45: =IFERROR(E45/ABS(D45),"n.s.") -> 2.5992601e-06
A46: ROA — Return on Asset (ROS × Asset Turnover) | C46: =C44*C45 -> 0.071450891 | D46: =D44*D45 -> 0.086497832 | E46: =C46-D46 -> -0.015046941 | F46: =IFERROR(E46/ABS(D46),"n.s.") -> -0.17395744
A47: ROE — Return on Equity (Utile netto / Patrimonio Netto) | C47: =C38/'Stato Patrimoniale'!C41 -> 0.10932344 | D47: =D38/'Stato Patrimoniale'!D41 -> 0.12786447 | E47: =C47-D47 -> -0.018541035 | F47: =IFERROR(E47/ABS(D47),"n.s.") -> -0.14500537
A48: Tax rate (Imposte / Risultato ante imposte) | C48: =-C37/C36 -> 0.14555053 | D48: =-D37/D36 -> 0.33870335 | E48: =C48-D48 -> -0.19315282 | F48: =IFERROR(E48/ABS(D48),"n.s.") -> -0.57027136
A49: Indice di sostenibilità degli oneri finanziari (Oneri finanziari / Ricavi) | C49: =-C35/C30 -> 0.025500471 | D49: =-D35/D30 -> 0.010387752 | E49: =C49-D49 -> 0.015112719 | F49: =IFERROR(E49/ABS(D49),"n.s.") -> 1.4548594
A52: 4. SINTESI STORICA 2021-2025 (andamento pluriennale)
A53: Voce | B53: 2021 | C53: 2022 | D53: 2023 | E53: 2024 | F53: 2025
A54: Fatturato / Ricavi netti | B54: 358539 | C54: 412074 | D54: 454199 | E54: =D6 -> 510120 | F54: =C6 -> 538343
A55: Costo del personale | B55: 95591 | C55: 105923 | D55: 110213 | E55: 121740 | F55: 126518
A57: Indicatori Cerved / ICAS (fonte: estratti CCIAA per 2021-23; ricalcolati per 2024-25)
A58: ROS — Return on Sales (EBIT / Fatturato) | B58: 0.15 | C58: 0.125 | D58: 0.138 | E58: =D14/D6 -> 0.13523485 | F58: =C14/C6 -> 0.11170945
A59: MOL / Ricavi (EBITDA margin) | B59: 0.184 | C59: 0.195 | D59: 0.197 | E59: =D22/D6 -> 0.19115698 | F59: =C22/C6 -> 0.20456103
A60: ROA (EBIT / Totale Attivo) | B60: 0.094 | C60: 0.081 | D60: 0.096 | E60: =D14/'Stato Patrimoniale'!D26 -> 0.086497832 | F60: =C14/'Stato Patrimoniale'!C26 -> 0.071450891
A61: ROE (Utile netto / Patrimonio Netto) | B61: 0.172 | C61: 0.148 | D61: 0.155 | E61: =D18/'Stato Patrimoniale'!D41 -> 0.12786447 | F61: =C18/'Stato Patrimoniale'!C41 -> 0.10932344
A62: ROI Cerved (EBIT / Capitale Investito Netto) | B62: 0.077 | C62: 0.086 | D62: 0.1 | E62: =D14/'Stato Patrimoniale'!D118 -> 0.12542179 | F62: =C14/'Stato Patrimoniale'!C118 -> 0.091920115
A64: Aggregati stimati 2021-2023 (Fatturato × indicatore Cerved) — 2024-2025 da Sezione 1
A65: EBITDA / MOL | B65: =B54*B59 -> 65971.176 | C65: =C54*C59 -> 80354.43 | D65: =D54*D59 -> 89477.203 | E65: =D22 -> 97513 | F65: =C22 -> 110124
A66: EBIT | B66: =B54*B58 -> 53780.85 | C66: =C54*C58 -> 51509.25 | D66: =D54*D58 -> 62679.462 | E66: =D14 -> 68986 | F66: =C14 -> 60138
A67: Utile Netto | B67: 36471 | C67: 37832 | D67: 45236 | E67: =D18 -> 42116 | F67: =C18 -> 39655

Sheet Rendiconto Finanziario
A1: FIDIA FARMACEUTICI S.p.A. — Cash Flow Statement
A2: Rendiconto Finanziario Consolidato — valori in migliaia di Euro, salvo diversa indicazione | V2: Tabella di supporto ai grafici
V3: Anno | W3: CFO | X3: CFI | Y3: CFF | Z3: Variazione Netta
A4: 1. RENDICONTO FINANZIARIO CONSOLIDATO IFRS (metodo indiretto) | V4: 2024 | W4: =E83 -> 41644 | X4: =E84 -> -210023 | Y4: =E85 -> 75605 | Z4: =E86 -> -92774
A5: Voce | C5: 2025 | D5: 2024 | E5: Variazione | F5: Var % | V5: 2025 | W5: =F83 -> 74510 | X5: =F84 -> -97977 | Y5: =F85 -> 12379 | Z5: =F86 -> -11088
A6: Flussi finanziari derivanti dall'attività di gestione
A7: Risultato netto dell'esercizio | C7: ='Conto Economico'!C18 -> 39655 | D7: ='Conto Economico'!D18 -> 42116 | E7: =C7-D7 -> -2461 | F7: =IFERROR(E7/ABS(D7),"n.s.") -> -0.058433849
A8: Imposte sul reddito | C8: 6755 | D8: 21571 | E8: =C8-D8 -> -14816 | F8: =IFERROR(E8/ABS(D8),"n.s.") -> -0.68684808 | V8: Tabella di supporto ai grafici
A9: Proventi e oneri finanziari | C9: 12393 | D9: 5715 | E9: =C9-D9 -> 6678 | F9: =IFERROR(E9/ABS(D9),"n.s.") -> 1.1685039 | V9: Anno | W9: Utile Netto
A10: (Plusvalenze)/minusvalenze derivanti dalla cessione di attività | C10: 8 | D10: 664 | E10: =C10-D10 -> -656 | F10: =IFERROR(E10/ABS(D10),"n.s.") -> -0.98795181 | V10: 2021 | W10: =B80 -> 36471
A11: Accantonamenti e utilizzo fondi | C11: -801 | D11: -1756 | E11: =C11-D11 -> 955 | F11: =IFERROR(E11/ABS(D11),"n.s.") -> 0.54384966 | V11: 2022 | W11: =C80 -> 37832
A12: Ammortamenti delle immobilizzazioni | C12: 44140 | D12: 27293 | E12: =C12-D12 -> 16847 | F12: =IFERROR(E12/ABS(D12),"n.s.") -> 0.6172645 | V12: 2023 | W12: =D80 -> 45236
A13: Svalutazioni per perdite durevoli di valore | C13: 1855 | D13: 297 | E13: =C13-D13 -> 1558 | F13: =IFERROR(E13/ABS(D13),"n.s.") -> 5.2457912 | V13: 2024 | W13: =E80 -> 42116
A14: Altre rettifiche per elementi non monetari | C14: 6719 | D14: 0 | E14: =C14-D14 -> 6719 | F14: =IFERROR(E14/ABS(D14),"n.s.") -> n.s. | V14: 2025 | W14: =F80 -> 39655
A15: Imposte sul reddito pagate | C15: -12911 | D15: -15312 | E15: =C15-D15 -> 2401 | F15: =IFERROR(E15/ABS(D15),"n.s.") -> 0.15680512
A16: Interessi pagati | C16: -11948 | D16: -6412 | E16: =C16-D16 -> -5536 | F16: =IFERROR(E16/ABS(D16),"n.s.") -> -0.86338116
A17: Flusso finanziario prima delle variazioni del CCN | C17: =SUM(C7:C16) -> 85865 | D17: =SUM(D7:D16) -> 74176 | E17: =C17-D17 -> 11689 | F17: =IFERROR(E17/ABS(D17),"n.s.") -> 0.15758466
A19: Capitale circolante
A20: Variazione crediti verso clienti | C20: 6201 | D20: -22368 | E20: =C20-D20 -> 28569 | F20: =IFERROR(E20/ABS(D20),"n.s.") -> 1.2772264
A21: Variazione rimanenze di magazzino | C21: 1222 | D21: -20394 | E21: =C21-D21 -> 21616 | F21: =IFERROR(E21/ABS(D21),"n.s.") -> 1.0599196
A22: Variazione altri crediti e altre attività correnti | C22: -3050 | D22: -8479 | E22: =C22-D22 -> 5429 | F22: =IFERROR(E22/ABS(D22),"n.s.") -> 0.64028777
A23: Variazione dei debiti verso fornitori | C23: -11673 | D23: 7018 | E23: =C23-D23 -> -18691 | F23: =IFERROR(E23/ABS(D23),"n.s.") -> -2.6632944
A24: Variazione altri debiti e altre passività correnti | C24: -1824 | D24: -4509 | E24: =C24-D24 -> 2685 | F24: =IFERROR(E24/ABS(D24),"n.s.") -> 0.59547572
A25: Variazione dei ratei e risconti attivi e passivi | C25: -2231 | D25: 16200 | E25: =C25-D25 -> -18431 | F25: =IFERROR(E25/ABS(D25),"n.s.") -> -1.137716
A26: Variazione dei crediti verso controllante | C26: 0 | D26: 0 | E26: =C26-D26 -> 0 | F26: =IFERROR(E26/ABS(D26),"n.s.") -> n.s.
A27: Variazione del capitale circolante | C27: =SUM(C20:C26) -> -11355 | D27: =SUM(D20:D26) -> -32532 | E27: =C27-D27 -> 21177 | F27: =IFERROR(E27/ABS(D27),"n.s.") -> 0.65095906
A28: DISPONIBILITÀ LIQUIDE GENERATE/(ASSORBITE) DALL'ATTIVITÀ DI GESTIONE | C28: =C17+C27 -> 74510 | D28: =D17+D27 -> 41644 | E28: =C28-D28 -> 32866 | F28: =IFERROR(E28/ABS(D28),"n.s.") -> 0.78921333
A30: Flussi finanziari derivanti dall'attività di investimento
A31: Investimenti netti in immobilizzazioni materiali | C31: -25490 | D31: -25476 | E31: =C31-D31 -> -14 | F31: =IFERROR(E31/ABS(D31),"n.s.") -> -0.00054953682
A32: Investimenti netti in immobilizzazioni immateriali | C32: -21133 | D32: -184303 | E32: =C32-D32 -> 163170 | F32: =IFERROR(E32/ABS(D32),"n.s.") -> 0.88533556
A33: Investimenti in immobilizzazioni finanziarie | C33: -38337 | D33: -244 | E33: =C33-D33 -> -38093 | F33: =IFERROR(E33/ABS(D33),"n.s.") -> -156.11885
A34: Acquisizione di partecipazioni | C34: -13017 | D34: 0 | E34: =C34-D34 -> -13017 | F34: =IFERROR(E34/ABS(D34),"n.s.") -> n.s.
A35: DISPONIBILITÀ LIQUIDE GENERATE/(ASSORBITE) DALL'ATTIVITÀ DI INVESTIMENTO | C35: =SUM(C31:C34) -> -97977 | D35: =SUM(D31:D34) -> -210023 | E35: =C35-D35 -> 112046 | F35: =IFERROR(E35/ABS(D35),"n.s.") -> 0.53349395
A37: Flussi finanziari derivanti dall'attività di finanziamento
A38: Accensione finanziamenti | C38: 62906 | D38: 129675 | E38: =C38-D38 -> -66769 | F38: =IFERROR(E38/ABS(D38),"n.s.") -> -0.51489493
A39: Rimborso finanziamenti | C39: -44739 | D39: -51739 | E39: =C39-D39 -> 7000 | F39: =IFERROR(E39/ABS(D39),"n.s.") -> 0.13529446
A40: Pagamento passività per leasing | C40: 336 | D40: -357 | E40: =C40-D40 -> 693 | F40: =IFERROR(E40/ABS(D40),"n.s.") -> 1.9411765
A41: Variazione debiti verso banche | C41: 0 | D41: 0 | E41: =C41-D41 -> 0 | F41: =IFERROR(E41/ABS(D41),"n.s.") -> n.s.
A42: Altre variazioni di patrimonio netto | C42: -2124 | D42: 1026 | E42: =C42-D42 -> -3150 | F42: =IFERROR(E42/ABS(D42),"n.s.") -> -3.0701754
A43: Dividendi distribuiti | C43: -4000 | D43: -3000 | E43: =C43-D43 -> -1000 | F43: =IFERROR(E43/ABS(D43),"n.s.") -> -0.33333333
A44: DISPONIBILITÀ LIQUIDE GENERATE/(ASSORBITE) DALL'ATTIVITÀ DI FINANZIAMENTO | C44: =SUM(C38:C43) -> 12379 | D44: =SUM(D38:D43) -> 75605 | E44: =C44-D44 -> -63226 | F44: =IFERROR(E44/ABS(D44),"n.s.") -> -0.83626744
A46: VARIAZIONE DELLE DISPONIBILITÀ LIQUIDE NETTE | C46: =C28+C35+C44 -> -11088 | D46: =D28+D35+D44 -> -92774 | E46: =C46-D46 -> 81686 | F46: =IFERROR(E46/ABS(D46),"n.s.") -> 0.88048376
A47: Disponibilità liquide e mezzi equivalenti all'inizio dell'esercizio | C47: ='Stato Patrimoniale'!D23 -> 47655 | D47: 140428 | E47: =C47-D47 -> -92773 | F47: =IFERROR(E47/ABS(D47),"n.s.") -> -0.6606446
A48: Differenze di cambio nette su disponibilità liquide e arrotondamenti (voce di quadratura) | C48: =('Stato Patrimoniale'!C23)-(C46+C47) -> 448 | D48: =('Stato Patrimoniale'!D23)-(D46+D47) -> 1
A49: DISPONIBILITÀ LIQUIDE E MEZZI EQUIVALENTI ALLA FINE DELL'ESERCIZIO | C49: =C46+C47+C48 -> 37015 | D49: =D46+D47+D48 -> 47655 | E49: =C49-D49 -> -10640 | F49: =IFERROR(E49/ABS(D49),"n.s.") -> -0.22327143
A50: Verifica (rispetto alle disponibilità liquide da Stato Patrimoniale) | C50: =C49-'Stato Patrimoniale'!C23 -> 0 | D50: =D49-'Stato Patrimoniale'!D23 -> 0
A52: Fonte: Fidia Farmaceutici S.p.A., Bilancio Consolidato al 31/12/2025, «Rendiconto Finanziario Consolidato», pag. 74-75/89. Valori in migliaia di Euro. Nota metodologica: nel documento originale il totale del flusso da attività di finanziamento e le disponibilità liquide iniziali/finali non sono riportati in forma pienamente esplicita per i due esercizi a confronto; i valori qui esposti sono stati ricostruiti e verificati per quadratura interna (somma dei componenti) e per coerenza con la «Situazione patrimoniale e finanziaria consolidata» e con il «Rendiconto finanziario consolidato sintetico» della Relazione sulla Gestione (pag. 52-53/89), da cui provengono anche le disponibilità liquide iniziali 2024 (Euro 140.428 migliaia). La voce «Differenze di cambio nette» è una posta di quadratura residuale (differenze cambio su disponibilità liquide di controllate estere e arrotondamenti in migliaia di Euro).
A56: 2. RENDICONTO FINANZIARIO RICLASSIFICATO — METODO ICAS (sezione 7, per aree gestionali)
A57: Voce | C57: 2025 | D57: 2024 | E57: Variazione | F57: Var %
A58: Autofinanziamento (flusso di cassa della gestione reddituale ante variazione CCN) | C58: =C17 -> 85865 | D58: =D17 -> 74176 | E58: =C58-D58 -> 11689 | F58: =IFERROR(E58/ABS(D58),"n.s.") -> 0.15758466
A59: Variazione del Capitale Circolante Netto | C59: =C27 -> -11355 | D59: =D27 -> -32532 | E59: =C59-D59 -> 21177 | F59: =IFERROR(E59/ABS(D59),"n.s.") -> 0.65095906
A60: FLUSSO DI CASSA DELLA GESTIONE OPERATIVA (CFO) | C60: =C58+C59 -> 74510 | D60: =D58+D59 -> 41644 | E60: =C60-D60 -> 32866 | F60: =IFERROR(E60/ABS(D60),"n.s.") -> 0.78921333
A61: Flusso di cassa della gestione degli investimenti (CFI) | C61: =C35 -> -97977 | D61: =D35 -> -210023 | E61: =C61-D61 -> 112046 | F61: =IFERROR(E61/ABS(D61),"n.s.") -> 0.53349395
A62: FREE CASH FLOW (CFO + CFI) | C62: =C60+C61 -> -23467 | D62: =D60+D61 -> -168379 | E62: =C62-D62 -> 144912 | F62: =IFERROR(E62/ABS(D62),"n.s.") -> 0.86062989
A63: Flusso di cassa della gestione finanziaria (CFF) | C63: =C44 -> 12379 | D63: =D44 -> 75605 | E63: =C63-D63 -> -63226 | F63: =IFERROR(E63/ABS(D63),"n.s.") -> -0.83626744
A64: FLUSSO DI CASSA NETTO DEL PERIODO | C64: =C62+C63 -> -11088 | D64: =D62+D63 -> -92774 | E64: =C64-D64 -> 81686 | F64: =IFERROR(E64/ABS(D64),"n.s.") -> 0.88048376
A65: Disponibilità liquide iniziali | C65: =C47 -> 47655 | D65: =D47 -> 140428 | E65: =C65-D65 -> -92773 | F65: =IFERROR(E65/ABS(D65),"n.s.") -> -0.6606446
A66: Differenze di cambio e arrotondamenti | C66: =C48 -> 448 | D66: =D48 -> 1 | E66: =C66-D66 -> 447 | F66: =IFERROR(E66/ABS(D66),"n.s.") -> 447
A67: DISPONIBILITÀ LIQUIDE FINALI | C67: =C64+C65+C66 -> 37015 | D67: =D64+D65+D66 -> 47655 | E67: =C67-D67 -> -10640 | F67: =IFERROR(E67/ABS(D67),"n.s.") -> -0.22327143
A69: 3. INDICATORI DI LIQUIDITÀ E SOSTENIBILITÀ DEL DEBITO ICAS
A70: Indicatore | C70: 2025 | D70: 2024 | E70: Variazione
A71: PFN (da Stato Patrimoniale riclassificato) | C71: ='Stato Patrimoniale'!C120 -> 307813 | D71: ='Stato Patrimoniale'!D120 -> 273998 | E71: =C71-D71 -> 33815 | F71: =IFERROR(E71/ABS(D71),"n.s.") -> 0.12341331
A72: EBITDA (da Conto Economico) | C72: ='Conto Economico'!C22 -> 110124 | D72: ='Conto Economico'!D22 -> 97513 | E72: =C72-D72 -> 12611 | F72: =IFERROR(E72/ABS(D72),"n.s.") -> 0.12932635
A73: PFN / EBITDA (Leva finanziaria) | C73: =C71/C72 -> 2.7951491 | D73: =D71/D72 -> 2.8098612 | E73: =C73-D73 -> -0.014712145 | F73: =IFERROR(E73/ABS(D73),"n.s.") -> -0.0052358972
A74: Free Cash Flow / Ricavi netti | C74: =C62/'Conto Economico'!C6 -> -0.043591168 | D74: =D62/'Conto Economico'!D6 -> -0.33007724 | E74: =C74-D74 -> 0.28648607 | F74: =IFERROR(E74/ABS(D74),"n.s.") -> 0.86793646
A75: Indice di ritorno liquido dell'attivo (CFO / Totale Attivo) | C75: =C60/'Stato Patrimoniale'!C26 -> 0.088526487 | D75: =D60/'Stato Patrimoniale'!D26 -> 0.05221517 | E75: =C75-D75 -> 0.036311317 | F75: =IFERROR(E75/ABS(D75),"n.s.") -> 0.69541701
A78: 4. SINTESI STORICA 2021-2025 (andamento pluriennale)
A79: Voce | B79: 2021 | C79: 2022 | D79: 2023 | E79: 2024 | F79: 2025
A80: Utile Netto (rinvio a Conto Economico — Sez. 4) | B80: ='Conto Economico'!B67 -> 36471 | C80: ='Conto Economico'!C67 -> 37832 | D80: ='Conto Economico'!D67 -> 45236 | E80: ='Conto Economico'!E67 -> 42116 | F80: ='Conto Economico'!F67 -> 39655
A82: Dettaglio flussi di cassa 2024-2025 (2021-2023 non disponibile dagli estratti camerali)
A83: Flusso di cassa della gestione operativa (CFO) | B83: n.d. | C83: n.d. | D83: n.d. | E83: =D28 -> 41644 | F83: =C28 -> 74510
A84: Flusso di cassa della gestione investimenti (CFI) | B84: n.d. | C84: n.d. | D84: n.d. | E84: =D35 -> -210023 | F84: =C35 -> -97977
A85: Flusso di cassa della gestione finanziaria (CFF) | B85: n.d. | C85: n.d. | D85: n.d. | E85: =D44 -> 75605 | F85: =C44 -> 12379
A86: VARIAZIONE NETTA DELLE DISPONIBILITÀ LIQUIDE | B86: n.d. | C86: n.d. | D86: n.d. | E86: =E83+E84+E85 -> -92774 | F86: =F83+F84+F85 -> -11088
